{
    "Имя функции: custom_sum. Время запуска: 2024-08-27 12:48:23.470433": {
        "Результат выполнения функции": 78,
        "Аргументы функции": {
            "позиционные аргументы": [
                10,
                23,
                -5,
                50
            ],
            "ключевые аргументы": {}
        }
    },
    "Имя функции: custom_sum_with_kwargs. Время запуска: 2024-08-27 12:48:23.470689": {
        "Результат выполнения функции": 4,
        "Аргументы функции": {
            "позиционные аргументы": [],
            "ключевые аргументы": {
                "a": 1,
                "b": 3
            }
        }
    }
}